phyde/__init__.py
phyde/bootstrap.py
phyde/data.cpp
phyde/data.pyx
phyde/result.py
phyde/utils.py
phyde-1.0.0.dist-info/LICENSE
phyde-1.0.0.dist-info/METADATA
phyde-1.0.0.dist-info/WHEEL
phyde-1.0.0.dist-info/top_level.txt
phyde-1.0.0.dist-info/RECORD
