Metadata-Version: 2.1
Name: phyde
Version: 1.0.0
Summary: Hybridization Detection Using Phylogenetic Invariants
Project-URL: Home, https://github.com/pblischak/HyDe
Project-URL: Issues, https://github.com/pblischak/HyDe/issues
Project-URL: Docs, http://hybridization-detection.readthedocs.io
Classifier: Programming Language :: Python
Classifier: Programming Language :: Python :: 3
Classifier: Programming Language :: Cython
Classifier: Development Status :: 5 - Production/Stable
Classifier: Intended Audience :: Science/Research
Classifier: License :: OSI Approved :: MIT License
Requires-Python: >=3.9
License-File: LICENSE
Requires-Dist: multiprocess
Requires-Dist: numpy
Requires-Dist: progress
